ezcsv/__init__.py
ezcsv-0.3.dist-info/DESCRIPTION.rst
ezcsv-0.3.dist-info/METADATA
ezcsv-0.3.dist-info/RECORD
ezcsv-0.3.dist-info/WHEEL
ezcsv-0.3.dist-info/metadata.json
ezcsv-0.3.dist-info/top_level.txt
