Metadata-Version: 2.0
Name: ezcsv
Version: 0.3
Summary: Functions to do obvious things with CSVs
Home-page: https://github.com/brandones/ezcsv
Author: Brandon Istenes
Author-email: brandonesbox@gmail.com
License: UNKNOWN
Project-URL: Source, https://github.com/brandones/ezcsv
Platform: UNKNOWN
